Workbook

Sheet statement of income
A1: Year | B1: Revenue | C1: Expenses | D1: Pretax Income | E1: Net Income
A2: 2023 | B2: 60515 | C2: 45079 | D2: 10513 | E2: 8374
A3: 2024 | B3: 65949 | C3: 47869 | D3: 12895 | E3: 10129
A4: 2025 | B4: 72229 | C4: 53178 | D4: 13795 | E4: 10833

Sheet revenues 
A1: Line Item | B1: 2023 | C1: 2024 | D1: 2025 | E1: yoy%24 | F1: yoy%2025
A2: Discount revenue | B2: 33416 | C2: 35192 | D2: 37401 | E2: =(C2-B2)/B2 -> 0.053148192 | F2: =(D2-C2)/C2 -> 0.062769948
A3: Net card fees | B3: 7255 | C3: 8449 | D3: 9993 | E3: =(C3-B3)/B3 -> 0.16457615 | F3: =(D3-C3)/C3 -> 0.18274352
A4: Service fees & other revenue | B4: 6710 | C4: 6765 | D4: 7471 | E4: =(C4-B4)/B4 -> 0.0081967213 | F4: =(D4-C4)/C4 -> 0.10436068
A5: Total non-interest revenues | B5: 47381 | C5: 50406 | D5: 54865 | E5: =(C5-B5)/B5 -> 0.063844157 | F5: =(D5-C5)/C5 -> 0.088461691
A6: Interest income | B6: 19983 | C6: 23795 | D6: 25598 | E6: =(C6-B6)/B6 -> 0.19076215 | F6: =(D6-C6)/C6 -> 0.075772221
A7: Interest expense | B7: 6849 | C7: 8252 | D7: 8234 | E7: =(C7-B7)/B7 -> 0.20484742 | F7: =(D7-C7)/C7 -> -0.0021812894
A8: Net interest income | B8: 13134 | C8: 15543 | D8: 17364 | E8: =(C8-B8)/B8 -> 0.18341709 | F8: =(D8-C8)/C8 -> 0.11715885
A9: Total revenues net of interest expense | B9: 60515 | C9: 65949 | D9: 72229 | E9: =(C9-B9)/B9 -> 0.089795918 | F9: =(D9-C9)/C9 -> 0.095225098

Sheet provisions 
A1: Line Item | B1: 2023 | C1: 2024 | D1: 2025 | E1: yoy2024% | F1: yoy2025%
A2: Provisions for credit losses | B2: 4923 | C2: 5185 | D2: 5256 | E2: =(C2-B2)/B2 -> 0.053219582 | F2: =(D2-C2)/C2 -> 0.013693346

Sheet expenses
A1: Line Item | B1: 2023 | C1: 2024 | D1: 2025 | E1: yoy2024% | F1: yoy2025%
A2: Card Member rewards | B2: 15367 | C2: 16599 | D2: 18409 | E2: =(C2-B2)/B2 -> 0.080171797 | F2: =(D2-C2)/C2 -> 0.10904271
A3: Business development | B3: 5657 | C3: 5886 | D3: 6457 | E3: =(C3-B3)/B3 -> 0.04048082 | F3: =(D3-C3)/C3 -> 0.097009854
A4: Card Member services | B4: 3968 | C4: 4782 | D4: 6057 | E4: =(C4-B4)/B4 -> 0.20514113 | F4: =(D4-C4)/C4 -> 0.26662484
A5: Marketing | B5: 5213 | C5: 6040 | D5: 6252 | E5: =(C5-B5)/B5 -> 0.15864186 | F5: =(D5-C5)/C5 -> 0.035099338
A6: Salaries & employee benefits | B6: 8067 | C6: 8198 | D6: 9016 | E6: =(C6-B6)/B6 -> 0.016238998 | F6: =(D6-C6)/C6 -> 0.099780434
A7: Other, net | B7: 6807 | C7: 6364 | D7: 6987 | E7: =(C7-B7)/B7 -> -0.065080065 | F7: =(D7-C7)/C7 -> 0.097894406
A8: Total expenses | B8: 45079 | C8: 47869 | D8: 53178 | E8: =(C8-B8)/B8 -> 0.061891346 | F8: =(D8-C8)/C8 -> 0.11090685

Sheet profit 
A1: Line Item | B1: 2023 | C1: 2024 | D1: 2025 | E1: yoy2024% | F1: yoy2025%
A2: Pretax income | B2: 10513 | C2: 12895 | D2: 13795 | E2: =(C2-B2)/B2 -> 0.22657662 | F2: =(D2-C2)/C2 -> 0.069794494
A3: Income tax provision | B3: 2139 | C3: 2766 | D3: 2962 | E3: =(C3-B3)/B3 -> 0.29312763 | F3: =(D3-C3)/C3 -> 0.070860448
A4: Net income | B4: 8374 | C4: 10129 | D4: 10833 | E4: =(C4-B4)/B4 -> 0.20957726 | F4: =(D4-C4)/C4 -> 0.069503406

Sheet margin analysis 
A1: Metric | B1: 2023 | C1: 2024 | D1: 2025
A2: Net Margin | B2: ='profit '!B4/'statement of income'!B2 -> 0.13837891 | C2: ='profit '!C4/'statement of income'!B3 -> 0.15358838 | D2: ='profit '!D4/'statement of income'!B4 -> 0.14998131
A3: Pretax Margin | B3: ='profit '!B2/'statement of income'!B2 -> 0.17372552 | C3: ='profit '!C2/'statement of income'!B3 -> 0.19552988 | D3: ='profit '!D2/'statement of income'!B4 -> 0.19098977
A4: Expense Ratio | B4: =expenses!B8/'statement of income'!B2 -> 0.74492275 | C4: =expenses!C8/Table6[[#This Row],[Revenue]] -> 0.66273934 | D4: =expenses!D8/'statement of income'!B4 -> 0.73624168
A5: Provision Ratio | B5: {=Table3[2023]/'statement of income'!B2} -> 0.081351731 | C5: {=Table3[2024]/'statement of income'!B3} -> 0.078621359 | D5: {=Table3[2025]/'statement of income'!B4} -> 0.072768556

Sheet Sheet2
A1: Year | B1: Revenue | C1: Expenses | D1: Pretax Income | E1: Net Income
A2: 2023 | B2: 60515 | C2: 45079 | D2: 10513 | E2: 8374
A3: 2024 | B3: 65949 | C3: 47869 | D3: 12895 | E3: 10129
A4: 2025 | B4: 72229 | C4: 53178 | D4: 13795 | E4: 10833

Sheet growth analysis 
A1: Metric | B1: 2024 Growth | C1: 2025 Growth
A2: Revenue Growth | B2: 0.0898 | C2: 0.0952
A3: Expense Growth | B3: 0.0619 | C3: 0.1109
A4: Net Income Growth | B4: 0.2096 | C4: 0.0695
A7: operating leverage impact | B7: Column1
A8: 2024 | B8: =B2-B3 -> 0.0279
A9: 2025 | B9: =C2-C3 -> -0.0157
A11: Profit conversion efficiency | B11: Column1
A12: 2024 | B12: =B4/B2 -> 2.3340757
A13: 2025 | B13: =C4/C2 -> 0.73004202

Sheet kpi summary 
A1: Revenue 2025 | B1: Net Margin 2025 | C1: Operating Leverage 2025 | D1: Provision Ratio 2025
A2: ='statement of income'!B4 -> 72229 | B2: =Table10[[#This Row],[2025]] -> 0.14998131 | C2: ='growth analysis '!B9 -> -0.0157 | D2: ='margin analysis '!D5 -> 0.072768556
